community_ai/___installer.py
community_ai/___loader.py
community_ai/__init__.py
pycommunity_ai-0.0.2.dist-info/LICENSE
pycommunity_ai-0.0.2.dist-info/METADATA
pycommunity_ai-0.0.2.dist-info/WHEEL
pycommunity_ai-0.0.2.dist-info/top_level.txt
pycommunity_ai-0.0.2.dist-info/RECORD
