Metadata-Version: 2.1
Name: pycommunity-ai
Version: 0.0.2
Summary: AI for all, all for AI
Author-email: trollmii <trollmii@outlook.de>
License: Apache License
Project-URL: Source, https://github.com/TrollMii/python-package
Requires-Python: >=3.8
License-File: LICENSE
